{
    "Fire points": {
        "G40072": {
            "properties": {
                "fire status": "Out",
                "fire cause": "Person",
                "object_id": 30229912,
                "location description": "Engn",
                "coordinates": {
                    "latitude": 54.0261,
                    "longitude": -124.2058
                },
                "ignition date": {
                    "complete": "2022-04-17",
                    "day": 17,
                    "month": 4,
                    "year": 2022
                }
            }
        },
        "C50071": {
            "properties": {
                "fire status": "Out",
                "fire cause": "Person",
                "object_id": 30229913,
                "location description": "Redstone Reserve",
                "coordinates": {
                    "latitude": 52.1425,
                    "longitude": -123.9607
                },
                "ignition date": {
                    "complete": "2022-04-17",
                    "day": 17,
                    "month": 4,
                    "year": 2022
                }
            }
        },
        "C20103": {
            "properties": {
                "fire status": "Out",
                "fire cause": "Person",
                "object_id": 30229914,
                "location description": "140 Mile House",
                "coordinates": {
                    "latitude": 51.9963,
                    "longitude": -121.8585
                },
                "ignition date": {
                    "complete": "2022-04-23",
                    "day": 23,
                    "month": 4,
                    "year": 2022
                }
            }
        },
        "C20104": {
            "properties": {
                "fire status": "Out",
                "fire cause": "Person",
                "object_id": 30229915,
                "location description": "Riske Creek",
                "coordinates": {
                    "latitude": 51.9524,
                    "longitude": -122.4285
                },
                "ignition date": {
                    "complete": "2022-04-23",
                    "day": 23,
                    "month": 4,
                    "year": 2022
                }
            }
        },
        "N10135": {
            "properties": {
                "fire status": "Out",
                "fire cause": "Person",
                "object_id": 30229916,
                "location description": "Matevic Rd",
                "coordinates": {
                    "latitude": 49.7441,
                    "longitude": -114.9027
                },
                "ignition date": {
                    "complete": "2022-04-30",
                    "day": 30,
                    "month": 4,
                    "year": 2022
                }
            }
        },
        "G80182": {
            "properties": {
                "fire status": "Out",
                "fire cause": "Person",
                "object_id": 30229917,
                "location description": "Bear Flats",
                "coordinates": {
                    "latitude": 56.285,
                    "longitude": -121.227
                },
                "ignition date": {
                    "complete": "2022-05-13",
                    "day": 13,
                    "month": 5,
                    "year": 2022
                }
            }
        },
        "K20084": {
            "properties": {
                "fire status": "Out",
                "fire cause": "Person",
                "object_id": 30229918,
                "location description": "Spatsum Creek",
                "coordinates": {
                    "latitude": 50.5631,
                    "longitude": -121.2946
                },
                "ignition date": {
                    "complete": "2022-04-20",
                    "day": 20,
                    "month": 4,
                    "year": 2022
                }
            }
        },
        "C50030": {
            "properties": {
                "fire status": "Out",
                "fire cause": "Person",
                "object_id": 30229919,
                "location description": "Hwy 20 W Alexis Creek",
                "coordinates": {
                    "latitude": 52.1089,
                    "longitude": -123.487
                },
                "ignition date": {
                    "complete": "2022-04-10",
                    "day": 10,
                    "month": 4,
                    "year": 2022
                }
            }
        },
        "C50029": {
            "properties": {
                "fire status": "Out",
                "fire cause": "Person",
                "object_id": 30229920,
                "location description": "Hwy 20 W Alexis Creek",
                "coordinates": {
                    "latitude": 52.113,
                    "longitude": -123.4431
                },
                "ignition date": {
                    "complete": "2022-04-10",
                    "day": 10,
                    "month": 4,
                    "year": 2022
                }
            }
        },
        "K20041": {
            "properties": {
                "fire status": "Out",
                "fire cause": "Unknown",
                "object_id": 30229921,
                "location description": "Meadow Road",
                "coordinates": {
                    "latitude": 50.8593,
                    "longitude": -120.6737
                },
                "ignition date": {
                    "complete": "2022-04-12",
                    "day": 12,
                    "month": 4,
                    "year": 2022
                }
            }
        },
        "G80265": {
            "properties": {
                "fire status": "Under Control",
                "fire cause": "Lightning",
                "object_id": 30229922,
                "location description": "North Side of Sikanni River",
                "coordinates": {
                    "latitude": 57.3972,
                    "longitude": -122.3773
                },
                "ignition date": {
                    "complete": "2022-06-03",
                    "day": 3,
                    "month": 6,
                    "year": 2022
                }
            }
        },
        "K70284": {
            "properties": {
                "fire status": "New",
                "fire cause": "Unknown",
                "object_id": 30229923,
                "location description": "Hwy 12",
                "coordinates": {
                    "latitude": 50.6197,
                    "longitude": -121.8479
                },
                "ignition date": {
                    "complete": "2022-06-08",
                    "day": 8,
                    "month": 6,
                    "year": 2022
                }
            }
        },
        "C50044": {
            "properties": {
                "fire status": "Out",
                "fire cause": "Person",
                "object_id": 30229924,
                "location description": "Junction Chezacut Rd and Hwy 20",
                "coordinates": {
                    "latitude": 52.1258,
                    "longitude": -123.6822
                },
                "ignition date": {
                    "complete": "2022-04-12",
                    "day": 12,
                    "month": 4,
                    "year": 2022
                }
            }
        },
        "N10082": {
            "properties": {
                "fire status": "Out",
                "fire cause": "Person",
                "object_id": 30229925,
                "location description": "Jaffery Baynes Lake Road",
                "coordinates": {
                    "latitude": 49.3101,
                    "longitude": -115.2868
                },
                "ignition date": {
                    "complete": "2022-04-18",
                    "day": 18,
                    "month": 4,
                    "year": 2022
                }
            }
        },
        "R40205": {
            "properties": {
                "fire status": "Out",
                "fire cause": "Person",
                "object_id": 30229926,
                "location description": "Skeena Crossing",
                "coordinates": {
                    "latitude": 55.1,
                    "longitude": -127.8124
                },
                "ignition date": {
                    "complete": "2022-05-21",
                    "day": 21,
                    "month": 5,
                    "year": 2022
                }
            }
        },
        "K60175": {
            "properties": {
                "fire status": "Out",
                "fire cause": "Person",
                "object_id": 30229927,
                "location description": "Coyle",
                "coordinates": {
                    "latitude": 50.138,
                    "longitude": -120.8659
                },
                "ignition date": {
                    "complete": "2022-05-11",
                    "day": 11,
                    "month": 5,
                    "year": 2022
                }
            }
        },
        "N60114": {
            "properties": {
                "fire status": "Under Control",
                "fire cause": "Person",
                "object_id": 30229928,
                "location description": "Rendell Creek",
                "coordinates": {
                    "latitude": 49.6401,
                    "longitude": -118.753
                },
                "ignition date": {
                    "complete": "2022-04-24",
                    "day": 24,
                    "month": 4,
                    "year": 2022
                }
            }
        },
        "K60119": {
            "properties": {
                "fire status": "Out",
                "fire cause": "Person",
                "object_id": 30229929,
                "location description": "Blackmine FSR",
                "coordinates": {
                    "latitude": 49.4073,
                    "longitude": -120.6125
                },
                "ignition date": {
                    "complete": "2022-04-25",
                    "day": 25,
                    "month": 4,
                    "year": 2022
                }
            }
        },
        "C50189": {
            "properties": {
                "fire status": "Out",
                "fire cause": "Person",
                "object_id": 30229930,
                "location description": "NE Nemaia Lake",
                "coordinates": {
                    "latitude": 51.4721,
                    "longitude": -123.9528
                },
                "ignition date": {
                    "complete": "2022-05-16",
                    "day": 16,
                    "month": 5,
                    "year": 2022
                }
            }
        },
        "K50177": {
            "properties": {
                "fire status": "Out",
                "fire cause": "Person",
                "object_id": 30229931,
                "location description": "5 km Carmi FSR",
                "coordinates": {
                    "latitude": 49.461,
                    "longitude": -119.3808
                },
                "ignition date": {
                    "complete": "2022-05-11",
                    "day": 11,
                    "month": 5,
                    "year": 2022
                }
            }
        },
        "C20179": {
            "properties": {
                "fire status": "Out",
                "fire cause": "Person",
                "object_id": 30229932,
                "location description": "2km S of Rodeo Rd",
                "coordinates": {
                    "latitude": 52.0396,
                    "longitude": -121.9044
                },
                "ignition date": {
                    "complete": "2022-05-11",
                    "day": 11,
                    "month": 5,
                    "year": 2022
                }
            }
        },
        "C20270": {
            "properties": {
                "fire status": "Out",
                "fire cause": "Person",
                "object_id": 30229933,
                "location description": "Williams Lake",
                "coordinates": {
                    "latitude": 52.2997,
                    "longitude": -122.1999
                },
                "ignition date": {
                    "complete": "2022-06-04",
                    "day": 4,
                    "month": 6,
                    "year": 2022
                }
            }
        },
        "V30039": {
            "properties": {
                "fire status": "Out",
                "fire cause": "Person",
                "object_id": 30229934,
                "location description": "South of Rancheree Road",
                "coordinates": {
                    "latitude": 50.3092,
                    "longitude": -122.7097
                },
                "ignition date": {
                    "complete": "2022-04-11",
                    "day": 11,
                    "month": 4,
                    "year": 2022
                }
            }
        },
        "C20226": {
            "properties": {
                "fire status": "Out",
                "fire cause": "Person",
                "object_id": 30229935,
                "location description": "White Rd",
                "coordinates": {
                    "latitude": 52.1202,
                    "longitude": -122.0481
                },
                "ignition date": {
                    "complete": "2022-05-24",
                    "day": 24,
                    "month": 5,
                    "year": 2022
                }
            }
        },
        "V70230": {
            "properties": {
                "fire status": "Out",
                "fire cause": "Person",
                "object_id": 30229936,
                "location description": "Cameron Lake",
                "coordinates": {
                    "latitude": 49.2888,
                    "longitude": -124.6266
                },
                "ignition date": {
                    "complete": "2022-05-26",
                    "day": 26,
                    "month": 5,
                    "year": 2022
                }
            }
        },
        "K20136": {
            "properties": {
                "fire status": "Out",
                "fire cause": "Person",
                "object_id": 30229937,
                "location description": "1.2 km Timber Lake FSR",
                "coordinates": {
                    "latitude": 50.5676,
                    "longitude": -120.4453
                },
                "ignition date": {
                    "complete": "2022-04-28",
                    "day": 28,
                    "month": 4,
                    "year": 2022
                }
            }
        },
        "K50156": {
            "properties": {
                "fire status": "Out",
                "fire cause": "Person",
                "object_id": 30229938,
                "location description": "Beaverdell Road",
                "coordinates": {
                    "latitude": 49.4679,
                    "longitude": -119.4955
                },
                "ignition date": {
                    "complete": "2022-05-05",
                    "day": 5,
                    "month": 5,
                    "year": 2022
                }
            }
        },
        "N10157": {
            "properties": {
                "fire status": "Out",
                "fire cause": "Person",
                "object_id": 30229939,
                "location description": "Baynes Lake",
                "coordinates": {
                    "latitude": 49.2224,
                    "longitude": -115.214
                },
                "ignition date": {
                    "complete": "2022-05-01",
                    "day": 1,
                    "month": 5,
                    "year": 2022
                }
            }
        },
        "C40221": {
            "properties": {
                "fire status": "Out",
                "fire cause": "Person",
                "object_id": 30229940,
                "location description": "Clinton Loon Lake FSR and Hwy 97",
                "coordinates": {
                    "latitude": 51.2343,
                    "longitude": -121.4985
                },
                "ignition date": {
                    "complete": "2022-05-24",
                    "day": 24,
                    "month": 5,
                    "year": 2022
                }
            }
        },
        "K70076": {
            "properties": {
                "fire status": "Out",
                "fire cause": "Person",
                "object_id": 30229941,
                "location description": "Olin Creek",
                "coordinates": {
                    "latitude": 50.7345,
                    "longitude": -122.1918
                },
                "ignition date": {
                    "complete": "2022-04-17",
                    "day": 17,
                    "month": 4,
                    "year": 2022
                }
            }
        },
        "C20073": {
            "properties": {
                "fire status": "Out",
                "fire cause": "Person",
                "object_id": 30229942,
                "location description": "Tlescoxeten Rd",
                "coordinates": {
                    "latitude": 51.9514,
                    "longitude": -122.5007
                },
                "ignition date": {
                    "complete": "2022-04-17",
                    "day": 17,
                    "month": 4,
                    "year": 2022
                }
            }
        },
        "C40075": {
            "properties": {
                "fire status": "Out",
                "fire cause": "Person",
                "object_id": 30229943,
                "location description": "Tin Cup Lake",
                "coordinates": {
                    "latitude": 51.353,
                    "longitude": -121.2091
                },
                "ignition date": {
                    "complete": "2022-04-17",
                    "day": 17,
                    "month": 4,
                    "year": 2022
                }
            }
        },
        "C50080": {
            "properties": {
                "fire status": "Out",
                "fire cause": "Person",
                "object_id": 30229944,
                "location description": "Redstone Reserve",
                "coordinates": {
                    "latitude": 52.1351,
                    "longitude": -123.9507
                },
                "ignition date": {
                    "complete": "2022-04-18",
                    "day": 18,
                    "month": 4,
                    "year": 2022
                }
            }
        },
        "C50190": {
            "properties": {
                "fire status": "Out",
                "fire cause": "Person",
                "object_id": 30229945,
                "location description": "Tatlayoko Lake",
                "coordinates": {
                    "latitude": 51.6281,
                    "longitude": -124.392
                },
                "ignition date": {
                    "complete": "2022-05-17",
                    "day": 17,
                    "month": 5,
                    "year": 2022
                }
            }
        },
        "N10009": {
            "properties": {
                "fire status": "Out",
                "fire cause": "Person",
                "object_id": 30229946,
                "location description": "Fort Steele area",
                "coordinates": {
                    "latitude": 49.6043,
                    "longitude": -115.6246
                },
                "ignition date": {
                    "complete": "2022-04-05",
                    "day": 5,
                    "month": 4,
                    "year": 2022
                }
            }
        },
        "G10224": {
            "properties": {
                "fire status": "Out",
                "fire cause": "Person",
                "object_id": 30229947,
                "location description": "HWY 16 E, Tabor Mtn Ski Resort",
                "coordinates": {
                    "latitude": 53.9145,
                    "longitude": -122.352
                },
                "ignition date": {
                    "complete": "2022-05-24",
                    "day": 24,
                    "month": 5,
                    "year": 2022
                }
            }
        },
        "G60264": {
            "properties": {
                "fire status": "Out",
                "fire cause": "Person",
                "object_id": 30229948,
                "location description": "Morfee Mountain",
                "coordinates": {
                    "latitude": 55.3763,
                    "longitude": -123.0883
                },
                "ignition date": {
                    "complete": "2022-06-03",
                    "day": 3,
                    "month": 6,
                    "year": 2022
                }
            }
        },
        "C50014": {
            "properties": {
                "fire status": "Out",
                "fire cause": "Person",
                "object_id": 30229949,
                "location description": "Dripping Water Rd",
                "coordinates": {
                    "latitude": 52.0402,
                    "longitude": -123.1765
                },
                "ignition date": {
                    "complete": "2022-04-07",
                    "day": 7,
                    "month": 4,
                    "year": 2022
                }
            }
        },
        "K40054": {
            "properties": {
                "fire status": "Out",
                "fire cause": "Person",
                "object_id": 30229950,
                "location description": "Turtle Valley",
                "coordinates": {
                    "latitude": 50.8164,
                    "longitude": -119.5427
                },
                "ignition date": {
                    "complete": "2022-04-14",
                    "day": 14,
                    "month": 4,
                    "year": 2022
                }
            }
        },
        "K40148": {
            "properties": {
                "fire status": "Out",
                "fire cause": "Unknown",
                "object_id": 30229951,
                "location description": "2km Talbot FSR",
                "coordinates": {
                    "latitude": 50.4338,
                    "longitude": -119.8187
                },
                "ignition date": {
                    "complete": "2022-05-02",
                    "day": 2,
                    "month": 5,
                    "year": 2022
                }
            }
        },
        "K40149": {
            "properties": {
                "fire status": "Out",
                "fire cause": "Unknown",
                "object_id": 30229952,
                "location description": "4km Station FSR",
                "coordinates": {
                    "latitude": 50.4889,
                    "longitude": -119.7333
                },
                "ignition date": {
                    "complete": "2022-05-02",
                    "day": 2,
                    "month": 5,
                    "year": 2022
                }
            }
        },
        "G40026": {
            "properties": {
                "fire status": "Out",
                "fire cause": "Person",
                "object_id": 30229953,
                "location description": "Fort Fraser",
                "coordinates": {
                    "latitude": 54.0535,
                    "longitude": -124.5302
                },
                "ignition date": {
                    "complete": "2022-04-09",
                    "day": 9,
                    "month": 4,
                    "year": 2022
                }
            }
        },
        "N20062": {
            "properties": {
                "fire status": "Out",
                "fire cause": "Person",
                "object_id": 30229954,
                "location description": "Whiteswan Lake",
                "coordinates": {
                    "latitude": 50.1201,
                    "longitude": -115.5448
                },
                "ignition date": {
                    "complete": "2022-04-15",
                    "day": 15,
                    "month": 4,
                    "year": 2022
                }
            }
        },
        "R10233": {
            "properties": {
                "fire status": "Out",
                "fire cause": "Person",
                "object_id": 30229955,
                "location description": "South Uncha Lake",
                "coordinates": {
                    "latitude": 53.9065,
                    "longitude": -125.6293
                },
                "ignition date": {
                    "complete": "2022-05-26",
                    "day": 26,
                    "month": 5,
                    "year": 2022
                }
            }
        },
        "G80257": {
            "properties": {
                "fire status": "Out",
                "fire cause": "Person",
                "object_id": 30229956,
                "location description": "21 km Upper Halfway Road",
                "coordinates": {
                    "latitude": 56.5214,
                    "longitude": -121.7823
                },
                "ignition date": {
                    "complete": "2022-06-02",
                    "day": 2,
                    "month": 6,
                    "year": 2022
                }
            }
        },
        "K40019": {
            "properties": {
                "fire status": "Out",
                "fire cause": "Person",
                "object_id": 30229957,
                "location description": "George Creek FSR",
                "coordinates": {
                    "latitude": 50.5174,
                    "longitude": -119.8777
                },
                "ignition date": {
                    "complete": "2022-04-08",
                    "day": 8,
                    "month": 4,
                    "year": 2022
                }
            }
        },
        "K20020": {
            "properties": {
                "fire status": "Out",
                "fire cause": "Person",
                "object_id": 30229958,
                "location description": "Lower Duck Range Road",
                "coordinates": {
                    "latitude": 50.6211,
                    "longitude": -119.8969
                },
                "ignition date": {
                    "complete": "2022-04-08",
                    "day": 8,
                    "month": 4,
                    "year": 2022
                }
            }
        },
        "V50244": {
            "properties": {
                "fire status": "Out",
                "fire cause": "Person",
                "object_id": 30229959,
                "location description": "Clack Creek",
                "coordinates": {
                    "latitude": 49.4613,
                    "longitude": -123.6241
                },
                "ignition date": {
                    "complete": "2022-05-29",
                    "day": 29,
                    "month": 5,
                    "year": 2022
                }
            }
        },
        "K60195": {
            "properties": {
                "fire status": "Out",
                "fire cause": "Person",
                "object_id": 30229960,
                "location description": "Corbett Lake",
                "coordinates": {
                    "latitude": 50.012,
                    "longitude": -120.6148
                },
                "ignition date": {
                    "complete": "2022-05-18",
                    "day": 18,
                    "month": 5,
                    "year": 2022
                }
            }
        },
        "C10011": {
            "properties": {
                "fire status": "Out",
                "fire cause": "Person",
                "object_id": 30229961,
                "location description": "Dragon Lake",
                "coordinates": {
                    "latitude": 52.9358,
                    "longitude": -122.4416
                },
                "ignition date": {
                    "complete": "2022-04-06",
                    "day": 6,
                    "month": 4,
                    "year": 2022
                }
            }
        },
        "K20016": {
            "properties": {
                "fire status": "Out",
                "fire cause": "Person",
                "object_id": 30229962,
                "location description": "Louis Creek 6km",
                "coordinates": {
                    "latitude": 50.7624,
                    "longitude": -120.0788
                },
                "ignition date": {
                    "complete": "2022-04-08",
                    "day": 8,
                    "month": 4,
                    "year": 2022
                }
            }
        },
        "K20017": {
            "properties": {
                "fire status": "Out",
                "fire cause": "Person",
                "object_id": 30229963,
                "location description": "5.5km Louis Lake FSR",
                "coordinates": {
                    "latitude": 50.7644,
                    "longitude": -120.0777
                },
                "ignition date": {
                    "complete": "2022-04-08",
                    "day": 8,
                    "month": 4,
                    "year": 2022
                }
            }
        },
        "K20018": {
            "properties": {
                "fire status": "Out",
                "fire cause": "Person",
                "object_id": 30229964,
                "location description": "Louis Creek FSR",
                "coordinates": {
                    "latitude": 50.7667,
                    "longitude": -120.0765
                },
                "ignition date": {
                    "complete": "2022-04-08",
                    "day": 8,
                    "month": 4,
                    "year": 2022
                }
            }
        },
        "V10035": {
            "properties": {
                "fire status": "Out",
                "fire cause": "Person",
                "object_id": 30229965,
                "location description": "Fraser Heritage Park",
                "coordinates": {
                    "latitude": 49.1441,
                    "longitude": -122.2824
                },
                "ignition date": {
                    "complete": "2022-04-10",
                    "day": 10,
                    "month": 4,
                    "year": 2022
                }
            }
        },
        "N10036": {
            "properties": {
                "fire status": "Out",
                "fire cause": "Person",
                "object_id": 30229966,
                "location description": "Gallaway FSR",
                "coordinates": {
                    "latitude": 49.4022,
                    "longitude": -115.2387
                },
                "ignition date": {
                    "complete": "2022-04-09",
                    "day": 9,
                    "month": 4,
                    "year": 2022
                }
            }
        },
        "K20051": {
            "properties": {
                "fire status": "Out",
                "fire cause": "Person",
                "object_id": 30229967,
                "location description": "Darfield",
                "coordinates": {
                    "latitude": 51.3109,
                    "longitude": -120.1638
                },
                "ignition date": {
                    "complete": "2022-04-13",
                    "day": 13,
                    "month": 4,
                    "year": 2022
                }
            }
        },
        "C50057": {
            "properties": {
                "fire status": "Out",
                "fire cause": "Person",
                "object_id": 30229968,
                "location description": "Anaham Flats",
                "coordinates": {
                    "latitude": 52.0077,
                    "longitude": -123.1562
                },
                "ignition date": {
                    "complete": "2022-04-15",
                    "day": 15,
                    "month": 4,
                    "year": 2022
                }
            }
        },
        "R40061": {
            "properties": {
                "fire status": "Out",
                "fire cause": "Person",
                "object_id": 30229969,
                "location description": "Gitwangak, Back Road",
                "coordinates": {
                    "latitude": 55.1007,
                    "longitude": -128.0593
                },
                "ignition date": {
                    "complete": "2022-04-15",
                    "day": 15,
                    "month": 4,
                    "year": 2022
                }
            }
        },
        "G30090": {
            "properties": {
                "fire status": "Out",
                "fire cause": "Person",
                "object_id": 30229970,
                "location description": "Crescent Spur on Loose Road",
                "coordinates": {
                    "latitude": 53.5434,
                    "longitude": -120.7078
                },
                "ignition date": {
                    "complete": "2022-04-22",
                    "day": 22,
                    "month": 4,
                    "year": 2022
                }
            }
        },
        "R40172": {
            "properties": {
                "fire status": "Out",
                "fire cause": "Person",
                "object_id": 30229971,
                "location description": "Kispiox Rodeo Grounds",
                "coordinates": {
                    "latitude": 55.4396,
                    "longitude": -127.7211
                },
                "ignition date": {
                    "complete": "2022-05-10",
                    "day": 10,
                    "month": 5,
                    "year": 2022
                }
            }
        },
        "C50024": {
            "properties": {
                "fire status": "Out",
                "fire cause": "Person",
                "object_id": 30229972,
                "location description": "Taseko Lake Rd",
                "coordinates": {
                    "latitude": 51.9234,
                    "longitude": -123.1089
                },
                "ignition date": {
                    "complete": "2022-04-09",
                    "day": 9,
                    "month": 4,
                    "year": 2022
                }
            }
        },
        "C50087": {
            "properties": {
                "fire status": "Out",
                "fire cause": "Person",
                "object_id": 30229973,
                "location description": "Fishtrap Rd",
                "coordinates": {
                    "latitude": 51.9897,
                    "longitude": -123.1471
                },
                "ignition date": {
                    "complete": "2022-04-21",
                    "day": 21,
                    "month": 4,
                    "year": 2022
                }
            }
        },
        "K20123": {
            "properties": {
                "fire status": "Out",
                "fire cause": "Person",
                "object_id": 30229974,
                "location description": "McGillivray Creek",
                "coordinates": {
                    "latitude": 50.8705,
                    "longitude": -119.9654
                },
                "ignition date": {
                    "complete": "2022-04-26",
                    "day": 26,
                    "month": 4,
                    "year": 2022
                }
            }
        },
        "C50143": {
            "properties": {
                "fire status": "Out",
                "fire cause": "Person",
                "object_id": 30229975,
                "location description": "Anahim Lake Airport",
                "coordinates": {
                    "latitude": 52.4436,
                    "longitude": -125.2944
                },
                "ignition date": {
                    "complete": "2022-05-02",
                    "day": 2,
                    "month": 5,
                    "year": 2022
                }
            }
        },
        "K20147": {
            "properties": {
                "fire status": "Out",
                "fire cause": "Unknown",
                "object_id": 30229976,
                "location description": "3km on McDougall FSR",
                "coordinates": {
                    "latitude": 51.607,
                    "longitude": -119.9763
                },
                "ignition date": {
                    "complete": "2022-05-01",
                    "day": 1,
                    "month": 5,
                    "year": 2022
                }
            }
        },
        "R40063": {
            "properties": {
                "fire status": "Out",
                "fire cause": "Person",
                "object_id": 30229977,
                "location description": "Kitwanga W Rd",
                "coordinates": {
                    "latitude": 55.1026,
                    "longitude": -128.0509
                },
                "ignition date": {
                    "complete": "2022-04-16",
                    "day": 16,
                    "month": 4,
                    "year": 2022
                }
            }
        },
        "C50068": {
            "properties": {
                "fire status": "Out",
                "fire cause": "Person",
                "object_id": 30229978,
                "location description": "Alexis Lake Rd",
                "coordinates": {
                    "latitude": 52.105,
                    "longitude": -123.4046
                },
                "ignition date": {
                    "complete": "2022-04-17",
                    "day": 17,
                    "month": 4,
                    "year": 2022
                }
            }
        },
        "G40138": {
            "properties": {
                "fire status": "Out",
                "fire cause": "Person",
                "object_id": 30229979,
                "location description": "Stoney Creek",
                "coordinates": {
                    "latitude": 53.9569,
                    "longitude": -124.1028
                },
                "ignition date": {
                    "complete": "2022-04-30",
                    "day": 30,
                    "month": 4,
                    "year": 2022
                }
            }
        },
        "K20140": {
            "properties": {
                "fire status": "Out",
                "fire cause": "Person",
                "object_id": 30229980,
                "location description": "Smith Camp Branch 1",
                "coordinates": {
                    "latitude": 50.7893,
                    "longitude": -120.8883
                },
                "ignition date": {
                    "complete": "2022-04-29",
                    "day": 29,
                    "month": 4,
                    "year": 2022
                }
            }
        },
        "K20139": {
            "properties": {
                "fire status": "Out",
                "fire cause": "Person",
                "object_id": 30229981,
                "location description": "George Creek",
                "coordinates": {
                    "latitude": 50.5565,
                    "longitude": -119.9008
                },
                "ignition date": {
                    "complete": "2022-04-29",
                    "day": 29,
                    "month": 4,
                    "year": 2022
                }
            }
        },
        "K20091": {
            "properties": {
                "fire status": "Out",
                "fire cause": "Person",
                "object_id": 30229982,
                "location description": "Goose Lake FSR",
                "coordinates": {
                    "latitude": 50.5562,
                    "longitude": -120.425
                },
                "ignition date": {
                    "complete": "2022-04-22",
                    "day": 22,
                    "month": 4,
                    "year": 2022
                }
            }
        },
        "K20125": {
            "properties": {
                "fire status": "Out",
                "fire cause": "Person",
                "object_id": 30229983,
                "location description": "16km George Creek FSR",
                "coordinates": {
                    "latitude": 50.5352,
                    "longitude": -120.0012
                },
                "ignition date": {
                    "complete": "2022-04-26",
                    "day": 26,
                    "month": 4,
                    "year": 2022
                }
            }
        },
        "N10153": {
            "properties": {
                "fire status": "Out",
                "fire cause": "Person",
                "object_id": 30229984,
                "location description": "Wycliff Cherry Creek Road",
                "coordinates": {
                    "latitude": 49.6344,
                    "longitude": -115.8648
                },
                "ignition date": {
                    "complete": "2022-05-04",
                    "day": 4,
                    "month": 5,
                    "year": 2022
                }
            }
        },
        "G30162": {
            "properties": {
                "fire status": "Out",
                "fire cause": "Person",
                "object_id": 30229985,
                "location description": "Swift Current Creek",
                "coordinates": {
                    "latitude": 53.0251,
                    "longitude": -119.2642
                },
                "ignition date": {
                    "complete": "2022-05-07",
                    "day": 7,
                    "month": 5,
                    "year": 2022
                }
            }
        },
        "R50258": {
            "properties": {
                "fire status": "Out",
                "fire cause": "Person",
                "object_id": 30229986,
                "location description": "Kitimat",
                "coordinates": {
                    "latitude": 53.9668,
                    "longitude": -128.6319
                },
                "ignition date": {
                    "complete": "2022-06-02",
                    "day": 2,
                    "month": 6,
                    "year": 2022
                }
            }
        },
        "G40259": {
            "properties": {
                "fire status": "Out",
                "fire cause": "Person",
                "object_id": 30229987,
                "location description": "Endako River",
                "coordinates": {
                    "latitude": 54.0686,
                    "longitude": -124.9619
                },
                "ignition date": {
                    "complete": "2022-06-02",
                    "day": 2,
                    "month": 6,
                    "year": 2022
                }
            }
        },
        "C50081": {
            "properties": {
                "fire status": "Out",
                "fire cause": "Person",
                "object_id": 30229988,
                "location description": "Anahim Meadow",
                "coordinates": {
                    "latitude": 52.114,
                    "longitude": -123.2359
                },
                "ignition date": {
                    "complete": "2022-04-18",
                    "day": 18,
                    "month": 4,
                    "year": 2022
                }
            }
        },
        "K20093": {
            "properties": {
                "fire status": "Out",
                "fire cause": "Person",
                "object_id": 30229989,
                "location description": "Timber Lake FSR",
                "coordinates": {
                    "latitude": 50.5864,
                    "longitude": -120.503
                },
                "ignition date": {
                    "complete": "2022-04-22",
                    "day": 22,
                    "month": 4,
                    "year": 2022
                }
            }
        },
        "R30194": {
            "properties": {
                "fire status": "Out",
                "fire cause": "Unknown",
                "object_id": 30229990,
                "location description": "Tatlow Rd",
                "coordinates": {
                    "latitude": 54.7724,
                    "longitude": -127.1397
                },
                "ignition date": {
                    "complete": "2022-05-17",
                    "day": 17,
                    "month": 5,
                    "year": 2022
                }
            }
        },
        "K20015": {
            "properties": {
                "fire status": "Out",
                "fire cause": "Person",
                "object_id": 30229991,
                "location description": "4 km Louis Lake FSR",
                "coordinates": {
                    "latitude": 50.7602,
                    "longitude": -120.0772
                },
                "ignition date": {
                    "complete": "2022-04-06",
                    "day": 6,
                    "month": 4,
                    "year": 2022
                }
            }
        },
        "C50027": {
            "properties": {
                "fire status": "Out",
                "fire cause": "Person",
                "object_id": 30229992,
                "location description": "Lee's Corner",
                "coordinates": {
                    "latitude": 51.9415,
                    "longitude": -123.0981
                },
                "ignition date": {
                    "complete": "2022-04-09",
                    "day": 9,
                    "month": 4,
                    "year": 2022
                }
            }
        },
        "K20164": {
            "properties": {
                "fire status": "Out",
                "fire cause": "Unknown",
                "object_id": 30229993,
                "location description": "Goose Lake FSR",
                "coordinates": {
                    "latitude": 50.5535,
                    "longitude": -120.4196
                },
                "ignition date": {
                    "complete": "2022-05-08",
                    "day": 8,
                    "month": 5,
                    "year": 2022
                }
            }
        },
        "K20184": {
            "properties": {
                "fire status": "Out",
                "fire cause": "Person",
                "object_id": 30229994,
                "location description": "Ivy Creek",
                "coordinates": {
                    "latitude": 51.6905,
                    "longitude": -119.4173
                },
                "ignition date": {
                    "complete": "2022-05-13",
                    "day": 13,
                    "month": 5,
                    "year": 2022
                }
            }
        },
        "C20232": {
            "properties": {
                "fire status": "Out",
                "fire cause": "Person",
                "object_id": 30229995,
                "location description": "White Rd",
                "coordinates": {
                    "latitude": 52.1193,
                    "longitude": -122.0504
                },
                "ignition date": {
                    "complete": "2022-05-26",
                    "day": 26,
                    "month": 5,
                    "year": 2022
                }
            }
        },
        "G80005": {
            "properties": {
                "fire status": "Out",
                "fire cause": "Person",
                "object_id": 30229996,
                "location description": "N side Doig Road S Osborne river",
                "coordinates": {
                    "latitude": 56.5891,
                    "longitude": -120.4236
                },
                "ignition date": {
                    "complete": "2022-04-02",
                    "day": 2,
                    "month": 4,
                    "year": 2022
                }
            }
        },
        "K60004": {
            "properties": {
                "fire status": "Out",
                "fire cause": "Person",
                "object_id": 30229997,
                "location description": "Mamit Lake Branch Road",
                "coordinates": {
                    "latitude": 50.1706,
                    "longitude": -120.8563
                },
                "ignition date": {
                    "complete": "2022-04-02",
                    "day": 2,
                    "month": 4,
                    "year": 2022
                }
            }
        },
        "C10008": {
            "properties": {
                "fire status": "Out",
                "fire cause": "Person",
                "object_id": 30229998,
                "location description": "Trudeau Rd",
                "coordinates": {
                    "latitude": 52.6038,
                    "longitude": -122.4659
                },
                "ignition date": {
                    "complete": "2022-04-02",
                    "day": 2,
                    "month": 4,
                    "year": 2022
                }
            }
        },
        "C50174": {
            "properties": {
                "fire status": "Out",
                "fire cause": "Person",
                "object_id": 30229999,
                "location description": "8km down Puntzi Lake Rd",
                "coordinates": {
                    "latitude": 52.1906,
                    "longitude": -124.0835
                },
                "ignition date": {
                    "complete": "2022-05-10",
                    "day": 10,
                    "month": 5,
                    "year": 2022
                }
            }
        },
        "K20192": {
            "properties": {
                "fire status": "Out",
                "fire cause": "Person",
                "object_id": 30230000,
                "location description": "Juniper Knoll",
                "coordinates": {
                    "latitude": 50.7885,
                    "longitude": -121.0739
                },
                "ignition date": {
                    "complete": "2022-05-17",
                    "day": 17,
                    "month": 5,
                    "year": 2022
                }
            }
        },
        "R90219": {
            "properties": {
                "fire status": "Out",
                "fire cause": "Unknown",
                "object_id": 30230001,
                "location description": "W of Moose Lake",
                "coordinates": {
                    "latitude": 59.6042,
                    "longitude": -133.5788
                },
                "ignition date": {
                    "complete": "2022-05-22",
                    "day": 22,
                    "month": 5,
                    "year": 2022
                }
            }
        },
        "G90274": {
            "properties": {
                "fire status": "Out of Control",
                "fire cause": "Lightning",
                "object_id": 30230002,
                "location description": "Vinatya Creek",
                "coordinates": {
                    "latitude": 59.9817,
                    "longitude": -120.0221
                },
                "ignition date": {
                    "complete": "2022-06-05",
                    "day": 5,
                    "month": 6,
                    "year": 2022
                }
            }
        },
        "R10052": {
            "properties": {
                "fire status": "Out",
                "fire cause": "Person",
                "object_id": 30230003,
                "location description": "Defoe Rd",
                "coordinates": {
                    "latitude": 54.3314,
                    "longitude": -125.8873
                },
                "ignition date": {
                    "complete": "2022-04-13",
                    "day": 13,
                    "month": 4,
                    "year": 2022
                }
            }
        },
        "G80210": {
            "properties": {
                "fire status": "Out",
                "fire cause": "Person",
                "object_id": 30230004,
                "location description": "Km 14.5 on Jedney Rd",
                "coordinates": {
                    "latitude": 57.0858,
                    "longitude": -122.0785
                },
                "ignition date": {
                    "complete": "2022-05-22",
                    "day": 22,
                    "month": 5,
                    "year": 2022
                }
            }
        },
        "R90255": {
            "properties": {
                "fire status": "Out",
                "fire cause": "Person",
                "object_id": 30230005,
                "location description": "Atlin",
                "coordinates": {
                    "latitude": 59.5816,
                    "longitude": -133.6448
                },
                "ignition date": {
                    "complete": "2022-06-01",
                    "day": 1,
                    "month": 6,
                    "year": 2022
                }
            }
        },
        "K60048": {
            "properties": {
                "fire status": "Out",
                "fire cause": "Person",
                "object_id": 30230006,
                "location description": "28 km Private Fsr",
                "coordinates": {
                    "latitude": 50.3236,
                    "longitude": -119.9731
                },
                "ignition date": {
                    "complete": "2022-04-10",
                    "day": 10,
                    "month": 4,
                    "year": 2022
                }
            }
        },
        "K60049": {
            "properties": {
                "fire status": "Out",
                "fire cause": "Person",
                "object_id": 30230007,
                "location description": "Salmon River 2",
                "coordinates": {
                    "latitude": 50.3171,
                    "longitude": -119.9704
                },
                "ignition date": {
                    "complete": "2022-04-10",
                    "day": 10,
                    "month": 4,
                    "year": 2022
                }
            }
        },
        "C50050": {
            "properties": {
                "fire status": "Out",
                "fire cause": "Person",
                "object_id": 30230008,
                "location description": "Chilko Newton Rd",
                "coordinates": {
                    "latitude": 52.0992,
                    "longitude": -123.5258
                },
                "ignition date": {
                    "complete": "2022-04-13",
                    "day": 13,
                    "month": 4,
                    "year": 2022
                }
            }
        },
        "K20115": {
            "properties": {
                "fire status": "Out",
                "fire cause": "Person",
                "object_id": 30230009,
                "location description": "23.5K Deadman Vidette",
                "coordinates": {
                    "latitude": 50.9653,
                    "longitude": -120.9506
                },
                "ignition date": {
                    "complete": "2022-04-25",
                    "day": 25,
                    "month": 4,
                    "year": 2022
                }
            }
        },
        "C40117": {
            "properties": {
                "fire status": "Out",
                "fire cause": "Person",
                "object_id": 30230010,
                "location description": "Eagan Lake Crescent",
                "coordinates": {
                    "latitude": 51.3799,
                    "longitude": -120.733
                },
                "ignition date": {
                    "complete": "2022-04-25",
                    "day": 25,
                    "month": 4,
                    "year": 2022
                }
            }
        },
        "K40042": {
            "properties": {
                "fire status": "Out",
                "fire cause": "Person",
                "object_id": 30230011,
                "location description": "25km Douglas Lake Road",
                "coordinates": {
                    "latitude": 50.3349,
                    "longitude": -119.97
                },
                "ignition date": {
                    "complete": "2022-04-10",
                    "day": 10,
                    "month": 4,
                    "year": 2022
                }
            }
        },
        "K20160": {
            "properties": {
                "fire status": "Out",
                "fire cause": "Person",
                "object_id": 30230012,
                "location description": "1.3km up Timber Lake FSR",
                "coordinates": {
                    "latitude": 50.5684,
                    "longitude": -120.4455
                },
                "ignition date": {
                    "complete": "2022-05-06",
                    "day": 6,
                    "month": 5,
                    "year": 2022
                }
            }
        },
        "N20249": {
            "properties": {
                "fire status": "Out",
                "fire cause": "Person",
                "object_id": 30230013,
                "location description": "Sheep Creek",
                "coordinates": {
                    "latitude": 49.9599,
                    "longitude": -115.7241
                },
                "ignition date": {
                    "complete": "2022-05-31",
                    "day": 31,
                    "month": 5,
                    "year": 2022
                }
            }
        },
        "K50275": {
            "properties": {
                "fire status": "Out",
                "fire cause": "Lightning",
                "object_id": 30230014,
                "location description": "K Mountain",
                "coordinates": {
                    "latitude": 49.1705,
                    "longitude": -119.7894
                },
                "ignition date": {
                    "complete": "2022-06-05",
                    "day": 5,
                    "month": 6,
                    "year": 2022
                }
            }
        },
        "C50045": {
            "properties": {
                "fire status": "Out",
                "fire cause": "Person",
                "object_id": 30230015,
                "location description": "5km W Chilko Newton Rd",
                "coordinates": {
                    "latitude": 52.0999,
                    "longitude": -123.5856
                },
                "ignition date": {
                    "complete": "2022-04-13",
                    "day": 13,
                    "month": 4,
                    "year": 2022
                }
            }
        },
        "C20208": {
            "properties": {
                "fire status": "Out",
                "fire cause": "Person",
                "object_id": 30230016,
                "location description": "Chimney Lake",
                "coordinates": {
                    "latitude": 51.9288,
                    "longitude": -121.9571
                },
                "ignition date": {
                    "complete": "2022-05-22",
                    "day": 22,
                    "month": 5,
                    "year": 2022
                }
            }
        },
        "G40217": {
            "properties": {
                "fire status": "Out",
                "fire cause": "Person",
                "object_id": 30230017,
                "location description": "Sutherland",
                "coordinates": {
                    "latitude": 54.1228,
                    "longitude": -124.6846
                },
                "ignition date": {
                    "complete": "2022-05-22",
                    "day": 22,
                    "month": 5,
                    "year": 2022
                }
            }
        },
        "V10229": {
            "properties": {
                "fire status": "Out",
                "fire cause": "Unknown",
                "object_id": 30230018,
                "location description": "Slollicum Creek",
                "coordinates": {
                    "latitude": 49.3869,
                    "longitude": -121.7413
                },
                "ignition date": {
                    "complete": "2022-05-25",
                    "day": 25,
                    "month": 5,
                    "year": 2022
                }
            }
        },
        "K40021": {
            "properties": {
                "fire status": "Out",
                "fire cause": "Person",
                "object_id": 30230019,
                "location description": "2 km on Arthur Creek FSR",
                "coordinates": {
                    "latitude": 50.5427,
                    "longitude": -119.5923
                },
                "ignition date": {
                    "complete": "2022-04-08",
                    "day": 8,
                    "month": 4,
                    "year": 2022
                }
            }
        },
        "C20033": {
            "properties": {
                "fire status": "Out",
                "fire cause": "Person",
                "object_id": 30230020,
                "location description": "West Fraser Rd",
                "coordinates": {
                    "latitude": 52.357,
                    "longitude": -122.369
                },
                "ignition date": {
                    "complete": "2022-04-10",
                    "day": 10,
                    "month": 4,
                    "year": 2022
                }
            }
        },
        "N60046": {
            "properties": {
                "fire status": "Out",
                "fire cause": "Person",
                "object_id": 30230021,
                "location description": "Midway Mill",
                "coordinates": {
                    "latitude": 49.0218,
                    "longitude": -118.8551
                },
                "ignition date": {
                    "complete": "2022-05-13",
                    "day": 13,
                    "month": 5,
                    "year": 2022
                }
            }
        },
        "C50047": {
            "properties": {
                "fire status": "Out",
                "fire cause": "Person",
                "object_id": 30230022,
                "location description": "6km W Chilko Newton Rd",
                "coordinates": {
                    "latitude": 52.0967,
                    "longitude": -123.6043
                },
                "ignition date": {
                    "complete": "2022-04-13",
                    "day": 13,
                    "month": 4,
                    "year": 2022
                }
            }
        },
        "C50056": {
            "properties": {
                "fire status": "Out",
                "fire cause": "Person",
                "object_id": 30230023,
                "location description": "Alexis Lake Rd",
                "coordinates": {
                    "latitude": 52.1375,
                    "longitude": -123.401
                },
                "ignition date": {
                    "complete": "2022-04-14",
                    "day": 14,
                    "month": 4,
                    "year": 2022
                }
            }
        },
        "K50003": {
            "properties": {
                "fire status": "Out",
                "fire cause": "Person",
                "object_id": 30230024,
                "location description": "Keremeos Bypass",
                "coordinates": {
                    "latitude": 49.2079,
                    "longitude": -119.8481
                },
                "ignition date": {
                    "complete": "2022-04-02",
                    "day": 2,
                    "month": 4,
                    "year": 2022
                }
            }
        },
        "C50002": {
            "properties": {
                "fire status": "Out",
                "fire cause": "Person",
                "object_id": 30230025,
                "location description": "S of Lee's Corner",
                "coordinates": {
                    "latitude": 51.9335,
                    "longitude": -123.0846
                },
                "ignition date": {
                    "complete": "2022-04-02",
                    "day": 2,
                    "month": 4,
                    "year": 2022
                }
            }
        },
        "K20150": {
            "properties": {
                "fire status": "Out",
                "fire cause": "Person",
                "object_id": 30230026,
                "location description": "Duck range/Hanna Road",
                "coordinates": {
                    "latitude": 50.6167,
                    "longitude": -119.8966
                },
                "ignition date": {
                    "complete": "2022-05-02",
                    "day": 2,
                    "month": 5,
                    "year": 2022
                }
            }
        },
        "C50155": {
            "properties": {
                "fire status": "Out",
                "fire cause": "Person",
                "object_id": 30230027,
                "location description": "Anahim Dump Rd",
                "coordinates": {
                    "latitude": 52.0032,
                    "longitude": -123.1391
                },
                "ignition date": {
                    "complete": "2022-05-05",
                    "day": 5,
                    "month": 5,
                    "year": 2022
                }
            }
        },
        "C50085": {
            "properties": {
                "fire status": "Out",
                "fire cause": "Person",
                "object_id": 30230028,
                "location description": "Anaham Reserve",
                "coordinates": {
                    "latitude": 52.0314,
                    "longitude": -123.1829
                },
                "ignition date": {
                    "complete": "2022-04-20",
                    "day": 20,
                    "month": 4,
                    "year": 2022
                }
            }
        },
        "K40131": {
            "properties": {
                "fire status": "Out",
                "fire cause": "Person",
                "object_id": 30230029,
                "location description": "Horseshoe Bay",
                "coordinates": {
                    "latitude": 50.9808,
                    "longitude": -119.1169
                },
                "ignition date": {
                    "complete": "2022-04-28",
                    "day": 28,
                    "month": 4,
                    "year": 2022
                }
            }
        },
        "K40141": {
            "properties": {
                "fire status": "Out",
                "fire cause": "Person",
                "object_id": 30230030,
                "location description": "6-7km George Creek FSR",
                "coordinates": {
                    "latitude": 50.5218,
                    "longitude": -119.8795
                },
                "ignition date": {
                    "complete": "2022-04-30",
                    "day": 30,
                    "month": 4,
                    "year": 2022
                }
            }
        },
        "C50142": {
            "properties": {
                "fire status": "Out",
                "fire cause": "Person",
                "object_id": 30230031,
                "location description": "Puntzi Lake Rd",
                "coordinates": {
                    "latitude": 52.1971,
                    "longitude": -124.0786
                },
                "ignition date": {
                    "complete": "2022-05-01",
                    "day": 1,
                    "month": 5,
                    "year": 2022
                }
            }
        },
        "N10145": {
            "properties": {
                "fire status": "Out",
                "fire cause": "Person",
                "object_id": 30230032,
                "location description": "Black Angus Rd",
                "coordinates": {
                    "latitude": 49.6052,
                    "longitude": -115.8636
                },
                "ignition date": {
                    "complete": "2022-05-01",
                    "day": 1,
                    "month": 5,
                    "year": 2022
                }
            }
        },
        "R10204": {
            "properties": {
                "fire status": "Out",
                "fire cause": "Person",
                "object_id": 30230033,
                "location description": "Uncha Lake",
                "coordinates": {
                    "latitude": 53.9324,
                    "longitude": -125.6589
                },
                "ignition date": {
                    "complete": "2022-05-21",
                    "day": 21,
                    "month": 5,
                    "year": 2022
                }
            }
        },
        "C20211": {
            "properties": {
                "fire status": "Out",
                "fire cause": "Person",
                "object_id": 30230034,
                "location description": "McInnis Rd",
                "coordinates": {
                    "latitude": 52.05,
                    "longitude": -122.1167
                },
                "ignition date": {
                    "complete": "2022-05-22",
                    "day": 22,
                    "month": 5,
                    "year": 2022
                }
            }
        },
        "G70213": {
            "properties": {
                "fire status": "Out",
                "fire cause": "Person",
                "object_id": 30230035,
                "location description": "Peace River",
                "coordinates": {
                    "latitude": 56.1608,
                    "longitude": -121.8373
                },
                "ignition date": {
                    "complete": "2022-05-22",
                    "day": 22,
                    "month": 5,
                    "year": 2022
                }
            }
        },
        "R40097": {
            "properties": {
                "fire status": "Out",
                "fire cause": "Person",
                "object_id": 30230036,
                "location description": "Suskwa FSR",
                "coordinates": {
                    "latitude": 55.2103,
                    "longitude": -127.4553
                },
                "ignition date": {
                    "complete": "2022-04-22",
                    "day": 22,
                    "month": 4,
                    "year": 2022
                }
            }
        },
        "R10111": {
            "properties": {
                "fire status": "Out",
                "fire cause": "Person",
                "object_id": 30230037,
                "location description": "Cheslatta River",
                "coordinates": {
                    "latitude": 53.7896,
                    "longitude": -125.8296
                },
                "ignition date": {
                    "complete": "2022-04-24",
                    "day": 24,
                    "month": 4,
                    "year": 2022
                }
            }
        },
        "C20110": {
            "properties": {
                "fire status": "Out",
                "fire cause": "Person",
                "object_id": 30230038,
                "location description": "Riske Creek Dump",
                "coordinates": {
                    "latitude": 51.9836,
                    "longitude": -122.6238
                },
                "ignition date": {
                    "complete": "2022-04-24",
                    "day": 24,
                    "month": 4,
                    "year": 2022
                }
            }
        },
        "N10132": {
            "properties": {
                "fire status": "Out",
                "fire cause": "Person",
                "object_id": 30230039,
                "location description": "Wardner Fort Steel Rd",
                "coordinates": {
                    "latitude": 49.4467,
                    "longitude": -115.4231
                },
                "ignition date": {
                    "complete": "2022-04-29",
                    "day": 29,
                    "month": 4,
                    "year": 2022
                }
            }
        },
        "K70158": {
            "properties": {
                "fire status": "Out",
                "fire cause": "Person",
                "object_id": 30230040,
                "location description": "6 km Laluwessen Road",
                "coordinates": {
                    "latitude": 50.4141,
                    "longitude": -121.6403
                },
                "ignition date": {
                    "complete": "2022-05-05",
                    "day": 5,
                    "month": 5,
                    "year": 2022
                }
            }
        },
        "C20269": {
            "properties": {
                "fire status": "Out",
                "fire cause": "Lightning",
                "object_id": 30230041,
                "location description": "South side of farwell canyon, lower 1/3 of slope 2",
                "coordinates": {
                    "latitude": 51.8115,
                    "longitude": -122.5384
                },
                "ignition date": {
                    "complete": "2022-06-03",
                    "day": 3,
                    "month": 6,
                    "year": 2022
                }
            }
        },
        "C10278": {
            "properties": {
                "fire status": "Out",
                "fire cause": "Person",
                "object_id": 30230042,
                "location description": "Milburn Lake",
                "coordinates": {
                    "latitude": 53.0218,
                    "longitude": -122.6808
                },
                "ignition date": {
                    "complete": "2022-06-06",
                    "day": 6,
                    "month": 6,
                    "year": 2022
                }
            }
        },
        "K60151": {
            "properties": {
                "fire status": "Out",
                "fire cause": "Person",
                "object_id": 30230043,
                "location description": "Rocky Pines",
                "coordinates": {
                    "latitude": 50.176,
                    "longitude": -120.8654
                },
                "ignition date": {
                    "complete": "2022-05-03",
                    "day": 3,
                    "month": 5,
                    "year": 2022
                }
            }
        },
        "C20235": {
            "properties": {
                "fire status": "Out",
                "fire cause": "Person",
                "object_id": 30230044,
                "location description": "White Rd",
                "coordinates": {
                    "latitude": 52.1196,
                    "longitude": -122.051
                },
                "ignition date": {
                    "complete": "2022-05-27",
                    "day": 27,
                    "month": 5,
                    "year": 2022
                }
            }
        },
        "V70013": {
            "properties": {
                "fire status": "Out",
                "fire cause": "Person",
                "object_id": 30230045,
                "location description": "Claymore Road W",
                "coordinates": {
                    "latitude": 49.3456,
                    "longitude": -124.5116
                },
                "ignition date": {
                    "complete": "2022-04-07",
                    "day": 7,
                    "month": 4,
                    "year": 2022
                }
            }
        },
        "C20012": {
            "properties": {
                "fire status": "Out",
                "fire cause": "Person",
                "object_id": 30230046,
                "location description": "Eagleview Rd",
                "coordinates": {
                    "latitude": 52.0651,
                    "longitude": -122.1192
                },
                "ignition date": {
                    "complete": "2022-04-07",
                    "day": 7,
                    "month": 4,
                    "year": 2022
                }
            }
        },
        "K20094": {
            "properties": {
                "fire status": "Out",
                "fire cause": "Person",
                "object_id": 30230047,
                "location description": "Mcconnell Lake, Lac Le Jeune",
                "coordinates": {
                    "latitude": 50.5248,
                    "longitude": -120.4725
                },
                "ignition date": {
                    "complete": "2022-04-22",
                    "day": 22,
                    "month": 4,
                    "year": 2022
                }
            }
        },
        "K60196": {
            "properties": {
                "fire status": "Out",
                "fire cause": "Person",
                "object_id": 30230048,
                "location description": "Summers Creek",
                "coordinates": {
                    "latitude": 49.5977,
                    "longitude": -120.4921
                },
                "ignition date": {
                    "complete": "2022-05-18",
                    "day": 18,
                    "month": 5,
                    "year": 2022
                }
            }
        },
        "G70212": {
            "properties": {
                "fire status": "Out",
                "fire cause": "Person",
                "object_id": 30230049,
                "location description": "Hwy 52",
                "coordinates": {
                    "latitude": 55.6474,
                    "longitude": -120.5611
                },
                "ignition date": {
                    "complete": "2022-05-22",
                    "day": 22,
                    "month": 5,
                    "year": 2022
                }
            }
        },
        "C40070": {
            "properties": {
                "fire status": "Out",
                "fire cause": "Person",
                "object_id": 30230050,
                "location description": "Bradley Creek Rd",
                "coordinates": {
                    "latitude": 51.8755,
                    "longitude": -121.1049
                },
                "ignition date": {
                    "complete": "1300-01-09",
                    "day": 9,
                    "month": 1,
                    "year": 1300
                }
            }
        },
        "K20165": {
            "properties": {
                "fire status": "Out",
                "fire cause": "Person",
                "object_id": 30230051,
                "location description": "13 Km Goose Lake FSR",
                "coordinates": {
                    "latitude": 50.5521,
                    "longitude": -120.4332
                },
                "ignition date": {
                    "complete": "2022-05-08",
                    "day": 8,
                    "month": 5,
                    "year": 2022
                }
            }
        },
        "K60262": {
            "properties": {
                "fire status": "Out",
                "fire cause": "Lightning",
                "object_id": 30230052,
                "location description": "Stumbles Creek",
                "coordinates": {
                    "latitude": 50.1773,
                    "longitude": -120.8808
                },
                "ignition date": {
                    "complete": "2022-06-02",
                    "day": 2,
                    "month": 6,
                    "year": 2022
                }
            }
        },
        "N20261": {
            "properties": {
                "fire status": "Out",
                "fire cause": "Person",
                "object_id": 30230053,
                "location description": "Johnson Road",
                "coordinates": {
                    "latitude": 49.9608,
                    "longitude": -115.7258
                },
                "ignition date": {
                    "complete": "2022-06-02",
                    "day": 2,
                    "month": 6,
                    "year": 2022
                }
            }
        },
        "K20086": {
            "properties": {
                "fire status": "Out",
                "fire cause": "Person",
                "object_id": 30230054,
                "location description": "1km up Timber Lake FSR",
                "coordinates": {
                    "latitude": 50.5697,
                    "longitude": -120.4478
                },
                "ignition date": {
                    "complete": "2022-04-20",
                    "day": 20,
                    "month": 4,
                    "year": 2022
                }
            }
        },
        "K50134": {
            "properties": {
                "fire status": "Out",
                "fire cause": "Person",
                "object_id": 30230055,
                "location description": "Drought Creek and Hwy 97c",
                "coordinates": {
                    "latitude": 49.8046,
                    "longitude": -119.6748
                },
                "ignition date": {
                    "complete": "2022-04-30",
                    "day": 30,
                    "month": 4,
                    "year": 2022
                }
            }
        },
        "K50200": {
            "properties": {
                "fire status": "Out",
                "fire cause": "Person",
                "object_id": 30230056,
                "location description": "Venner Creek",
                "coordinates": {
                    "latitude": 49.8329,
                    "longitude": -119.7897
                },
                "ignition date": {
                    "complete": "2022-05-20",
                    "day": 20,
                    "month": 5,
                    "year": 2022
                }
            }
        },
        "K70214": {
            "properties": {
                "fire status": "Out",
                "fire cause": "Person",
                "object_id": 30230057,
                "location description": "Skiel Mountain",
                "coordinates": {
                    "latitude": 50.7221,
                    "longitude": -122.2452
                },
                "ignition date": {
                    "complete": "2022-05-22",
                    "day": 22,
                    "month": 5,
                    "year": 2022
                }
            }
        },
        "G70216": {
            "properties": {
                "fire status": "Out",
                "fire cause": "Person",
                "object_id": 30230058,
                "location description": "Williston Lake",
                "coordinates": {
                    "latitude": 56.1202,
                    "longitude": -122.3208
                },
                "ignition date": {
                    "complete": "2022-05-23",
                    "day": 23,
                    "month": 5,
                    "year": 2022
                }
            }
        },
        "K20228": {
            "properties": {
                "fire status": "Out",
                "fire cause": "Person",
                "object_id": 30230059,
                "location description": "Buse Creek",
                "coordinates": {
                    "latitude": 50.6421,
                    "longitude": -120.0037
                },
                "ignition date": {
                    "complete": "2022-05-25",
                    "day": 25,
                    "month": 5,
                    "year": 2022
                }
            }
        },
        "K40236": {
            "properties": {
                "fire status": "Out",
                "fire cause": "Person",
                "object_id": 30230060,
                "location description": "20 Km South of Sicamous",
                "coordinates": {
                    "latitude": 50.8138,
                    "longitude": -119.0489
                },
                "ignition date": {
                    "complete": "2022-05-27",
                    "day": 27,
                    "month": 5,
                    "year": 2022
                }
            }
        },
        "C20238": {
            "properties": {
                "fire status": "Out",
                "fire cause": "Person",
                "object_id": 30230061,
                "location description": "Chimney Lake Rd",
                "coordinates": {
                    "latitude": 51.9281,
                    "longitude": -121.9637
                },
                "ignition date": {
                    "complete": "2022-05-27",
                    "day": 27,
                    "month": 5,
                    "year": 2022
                }
            }
        },
        "C20043": {
            "properties": {
                "fire status": "Out",
                "fire cause": "Person",
                "object_id": 30230062,
                "location description": "Riske Creek",
                "coordinates": {
                    "latitude": 51.9836,
                    "longitude": -122.6263
                },
                "ignition date": {
                    "complete": "2022-04-12",
                    "day": 12,
                    "month": 4,
                    "year": 2022
                }
            }
        },
        "2022-06-08": {}
    }
}